examples/__init__.py
examples/simple.py
marquez_client/__init__.py
marquez_client/client.py
marquez_client/clients.py
marquez_client/constants.py
marquez_client/errors.py
marquez_client/models.py
marquez_client/utils.py
tests/__init__.py
tests/test_marquez_client.py
tests/test_marquez_clients.py
tests/test_utils.py
marquez_python-0.50.0.dist-info/METADATA
marquez_python-0.50.0.dist-info/WHEEL
marquez_python-0.50.0.dist-info/top_level.txt
marquez_python-0.50.0.dist-info/RECORD
