Metadata-Version: 2.1
Name: marquez-python
Version: 0.50.0
Summary: Marquez Python Client
Home-page: UNKNOWN
Author: Marquez Project
License: UNKNOWN
Keywords: marquez
Platform: UNKNOWN
Requires-Python: >=3.6
Requires-Dist: requests
Requires-Dist: six
Requires-Dist: pyrfc3339
Requires-Dist: deprecation
Provides-Extra: dev
Requires-Dist: pytest ; extra == 'dev'
Requires-Dist: flake8 ; extra == 'dev'
Requires-Dist: pytest-cov ; extra == 'dev'
Requires-Dist: mock ; extra == 'dev'
Provides-Extra: tests
Requires-Dist: pytest ; extra == 'tests'
Requires-Dist: pytest-cov ; extra == 'tests'
Requires-Dist: mock ; extra == 'tests'
Requires-Dist: flake8 ; extra == 'tests'
